rest_extensions/__init__.py
rest_extensions/admin.py
rest_extensions/apps.py
rest_extensions/authentication.py
rest_extensions/fields.py
rest_extensions/filters.py
rest_extensions/middleware.py
rest_extensions/mixins.py
rest_extensions/models.py
rest_extensions/paginations.py
rest_extensions/permissions.py
rest_extensions/serializers.py
rest_extensions/tests.py
rest_extensions/urls.py
rest_extensions/utils.py
rest_extensions/views.py
rest_extensions/migrations/__init__.py
django_rest_extensions-1.2.1.dist-info/LICENSE
django_rest_extensions-1.2.1.dist-info/METADATA
django_rest_extensions-1.2.1.dist-info/WHEEL
django_rest_extensions-1.2.1.dist-info/top_level.txt
django_rest_extensions-1.2.1.dist-info/RECORD
