Metadata-Version: 2.1
Name: django-rest-extensions
Version: 1.2.1
Summary: create normal api for all your models
Home-page: https://github.com/ramwin/django-rest-extensions
Author: Xiang Wang
Author-email: ramwin@qq.com
Classifier: Programming Language :: Python :: 2
Classifier: Programming Language :: Python :: 3
Classifier: License :: OSI Approved :: GNU Affero General Public License v3 or later (AGPLv3+)
Classifier: Operating System :: OS Independent
License-File: LICENSE
Requires-Dist: django >=2
Requires-Dist: djangorestframework
